casarecipes/__init__.py
casarecipes/almahelpers.py
casarecipes/almapolhelpers.py
casarecipes/astro_stations2simdata.py
casarecipes/atcapolhelpers.py
casarecipes/automask.py
casarecipes/benchmark.py
casarecipes/calc_calibratorflux.py
casarecipes/checkdataformat.py
casarecipes/checknan.py
casarecipes/cl2skycat.py
casarecipes/cmpmses.py
casarecipes/commongrid.py
casarecipes/drawmaskinimage.py
casarecipes/ephemerides/concatephem.py
casarecipes/ephemerides/convertephem.py
casarecipes/ephemerides/ssobjAngDiam.py
casarecipes/field2skycat.py
casarecipes/find_autocorr.py
casarecipes/free_disk_space.py
casarecipes/gaincal_unflag_nearest.py
casarecipes/getazel.py
casarecipes/imager_resource_predictor.py
casarecipes/linfeedpolhelpers.py
casarecipes/listshapes.py
casarecipes/lsms.py
casarecipes/make_labelled_ms.py
casarecipes/makepb.py
casarecipes/opacity.py
casarecipes/pixelmask2cleanmask.py
casarecipes/plotazel.py
casarecipes/psplit.py
casarecipes/remove_cloud.py
casarecipes/setOrder.py
casarecipes/specframeconvert.py
casarecipes/taskutil.py
casarecipes/weights.py
casarecipes/_version.py
casarecipes-0.4.0.dist-info/WHEEL
casarecipes-0.4.0.dist-info/METADATA
casarecipes-0.4.0.dist-info/licenses/LICENSE
casarecipes-0.4.0.dist-info/RECORD
