Metadata-Version: 2.1
Name: casarecipes
Version: 0.4.0
Summary: CASA recipes
License: LGPL
Author-email: Marcel de Casa <marcel.decasa@gmail.com>
Requires-Python: >=3.6
